LICENSE
README.md
setup.py
cloudify_importer/__init__.py
cloudify_importer/loader.py
cloudify_python_importer.egg-info/PKG-INFO
cloudify_python_importer.egg-info/SOURCES.txt
cloudify_python_importer.egg-info/dependency_links.txt
cloudify_python_importer.egg-info/top_level.txt