Metadata-Version: 2.1
Name: cloudify-python-importer
Version: 0.2.1
Summary: Plugin provides Kubernetes management possibility
Author: Cloudify Team
Author-email: hello@getcloudify.org
License: LICENSE
License-File: LICENSE
